wxyz/html/__init__.py
wxyz/html/_version.py
wxyz/html/base.py
wxyz/html/install.json
wxyz/html/widget_color.py
wxyz/html/widget_file.py
wxyz/html/widget_fullscreen.py
wxyz/html/js/LICENSE.txt
wxyz/html/js/README.md
wxyz/html/js/package.json
wxyz/html/labextension/package.json
wxyz/html/labextension/static/165.c0f7041ff175c386a41f.js
wxyz/html/labextension/static/333.739536b05d3283410076.js
wxyz/html/labextension/static/445.4606975cacd91d110826.js
wxyz/html/labextension/static/445.4606975cacd91d110826.js.LICENSE.txt
wxyz/html/labextension/static/568.2ed45ca356765f23db7f.js
wxyz/html/labextension/static/601.ef78d24a222bff54dd97.js
wxyz/html/labextension/static/remoteEntry.4cbc586e88f654967ac2.js
wxyz/html/labextension/static/style.js
wxyz_html-0.5.1.data/data/share/jupyter/labextensions/@deathbeds/wxyz-html/install.json
wxyz_html-0.5.1.data/data/share/jupyter/labextensions/@deathbeds/wxyz-html/package.json
wxyz_html-0.5.1.data/data/share/jupyter/labextensions/@deathbeds/wxyz-html/static/165.c0f7041ff175c386a41f.js
wxyz_html-0.5.1.data/data/share/jupyter/labextensions/@deathbeds/wxyz-html/static/333.739536b05d3283410076.js
wxyz_html-0.5.1.data/data/share/jupyter/labextensions/@deathbeds/wxyz-html/static/445.4606975cacd91d110826.js
wxyz_html-0.5.1.data/data/share/jupyter/labextensions/@deathbeds/wxyz-html/static/445.4606975cacd91d110826.js.LICENSE.txt
wxyz_html-0.5.1.data/data/share/jupyter/labextensions/@deathbeds/wxyz-html/static/568.2ed45ca356765f23db7f.js
wxyz_html-0.5.1.data/data/share/jupyter/labextensions/@deathbeds/wxyz-html/static/601.ef78d24a222bff54dd97.js
wxyz_html-0.5.1.data/data/share/jupyter/labextensions/@deathbeds/wxyz-html/static/remoteEntry.4cbc586e88f654967ac2.js
wxyz_html-0.5.1.data/data/share/jupyter/labextensions/@deathbeds/wxyz-html/static/style.js
wxyz_html-0.5.1.dist-info/LICENSE.txt
wxyz_html-0.5.1.dist-info/METADATA
wxyz_html-0.5.1.dist-info/WHEEL
wxyz_html-0.5.1.dist-info/top_level.txt
wxyz_html-0.5.1.dist-info/RECORD
